{
  "id": "3_2",
  "header": "3.2 Zielsetzung (R+AS)",
  "header_hierarchy": [
    {
      "level": 2,
      "number": "3.2",
      "title": "Zielsetzung (R+AS)"
    }
  ],
  "content": "Jede Institution braucht eine individuelle Zielsetzung für ein angemessenes BCM. Diese \nlässt sich aus den Geschäftsprozessen bzw. Fachaufgaben, den gesetzlichen Rahmenbe­\ndingungen und insbesondere den jeweiligen Institutionszielen ableiten. Die Institutions­\nleitung muss die Ziele für das BCM vorgeben und sie innerhalb der Institution kommuni­\nzieren, sodass alle Mitarbeitenden erreicht werden. Es ist empfehlenswert, dies über die \nLeitlinie BCMS sicherzustellen (siehe 4.8.2 Veröffentlichung und Aktualisierung der Leit­\nlinie BCMS (R+AS)). Die Leitung setzt ein klares Startsignal, indem sie sämtlichen Interes­\nsengruppen der Institution die Ziele des BCM bekannt gibt. Gleichzeitig vergibt die Insti­\ntutionsleitung den dafür notwendigen Arbeitsauftrag an die taktische und operative \nEbene.\n\nDie Ziele des BCM müssen zu den Anforderungen an das BCMS und zu der strategischen \nAusrichtung der Institution passen und sollten unmittelbar die Gründe und hier insbe­\nsondere die verpflichtenden externen Gründe für ein BCMS berücksichtigen. Darüber \nhinaus sollten die definierten Ziele messbar sein, sofern dies sinnvoll umsetzbar ist.\n\nDie Zielsetzung geht vorrangig auf drei Fragen ein:\n\n• \nWarum wird in der Institution ein BCM benötigt? (Motivation für den Aufbau eines \nBCMS)\n\n• \nWelche konkreten Ziele werden mit dem BCM verfolgt?\n\n• \nWie lange soll durch das BCM ein Ausfall des Normalbetriebs kompensiert werden? \n(Abzusichernder Zeitraum durch ein BCM)",
  "pages": {
    "start": 51,
    "end": 52
  },
  "modal_verben": [],
  "source": {
    "document": "standard_200_4",
    "file": "standard_200_4.pdf"
  }
}